test_plugin/__init__.py
test_plugin/admin.py
test_plugin/apps.py
test_plugin/forms.py
test_plugin/models.py
test_plugin/tests.py
test_plugin/urls.py
test_plugin/views.py
test_plugin/migrations/__init__.py
test_plugin_testy/__init__.py
test_plugin_testy/admin.py
test_plugin_testy/apps.py
test_plugin_testy/forms.py
test_plugin_testy/models.py
test_plugin_testy/tests.py
test_plugin_testy/urls.py
test_plugin_testy/views.py
test_plugin_testy/migrations/__init__.py
test_plugin_testy/templates/upload_form.html
test_plugin_testy/templates/upload_success.html
test_plugin_testy-0.5.dist-info/METADATA
test_plugin_testy-0.5.dist-info/WHEEL
test_plugin_testy-0.5.dist-info/entry_points.txt
test_plugin_testy-0.5.dist-info/top_level.txt
test_plugin_testy-0.5.dist-info/RECORD
